{
  "hash": "bc4489b4",
  "configHash": "73bfdfa2",
  "lockfileHash": "0b2f2783",
  "browserHash": "2d2c3694",
  "optimized": {
    "react": {
      "src": "../../node_modules/react/index.js",
      "file": "react.js",
      "fileHash": "7692badb",
      "needsInterop": true
    },
    "react-dom/client": {
      "src": "../../node_modules/react-dom/client.js",
      "file": "react-dom_client.js",
      "fileHash": "9151fa68",
      "needsInterop": true
    }
  },
  "chunks": {
    "chunk-XFZ2DVVZ": {
      "file": "chunk-XFZ2DVVZ.js"
    }
  }
}